{
  "ComboPerformance": {},
  "CardCounters": {
    "0": {
      "CardId": 0,
      "EffectiveCounters": [
        14315573,
        68005187,
        18807109,
        511000822,
        97590747,
        18144507,
        66602787,
        4031928,
        6740720
      ]
    }
  },
  "StageSpecificCombos": {
    "Late": [
      [
        68516705,
        12580477
      ],
      [
        14898066,
        4031928
      ],
      [
        87564352,
        55144522,
        68005187
      ],
      [
        66602787,
        18144507
      ],
      [
        54912977,
        68005187
      ],
      [
        13945283,
        22046459
      ],
      [
        72892473,
        13945283
      ],
      [
        54652250,
        54912977
      ],
      [
        79571449,
        12580477,
        83764719
      ],
      [
        79571449,
        13039848,
        83764719
      ],
      [
        7089711,
        48642904
      ],
      [
        68516705,
        79571449
      ],
      [
        7089711,
        4031928
      ],
      [
        68516705,
        55144522
      ],
      [
        68516705,
        55144522,
        83764719
      ],
      [
        68516705,
        55144522,
        83764719,
        22046459
      ]
    ],
    "Mid": [
      [
        68516705,
        72892473,
        83764719
      ],
      [
        68516705,
        79571449,
        48642904
      ],
      [
        5053103,
        48642904
      ],
      [
        68516705,
        55144522,
        12580477,
        72892473
      ],
      [
        97590747,
        12580477
      ],
      [
        511003012,
        12580477,
        48642904
      ],
      [
        68516705,
        79571449
      ],
      [
        68516705,
        68005187,
        22046459
      ],
      [
        34124316,
        68005187
      ],
      [
        7089711,
        12580477
      ],
      [
        79571449,
        13039848
      ],
      [
        511002631,
        12580477,
        83764719
      ],
      [
        5053103,
        4031928
      ],
      [
        6740720,
        18144507,
        72892473
      ],
      [
        87564352,
        18144507
      ]
    ]
  },
  "LastUpdated": "4/8/2025 5:54:40 PM"
}